{
  "as_of": "2026-03-20",
  "NATURALGAS": [
    {
      "expiry": "26MAR2026",
      "dte": 6,
      "total_margin_pct": 34.26,
      "vol_daily": 0.044598,
      "predicted_tomorrow": 32.272,
      "spread_vs_prev": 0.86,
      "action": "CUT"
    },
    {
      "expiry": "26MAR2026",
      "dte": 6,
      "total_margin_pct": 33.4,
      "vol_daily": 0.043382,
      "predicted_tomorrow": 31.458,
      "spread_vs_prev": 0.06,
      "action": "CUT"
    },
    {
      "expiry": "26MAR2026",
      "dte": 6,
      "total_margin_pct": 33.34,
      "vol_daily": 0.043301,
      "predicted_tomorrow": 31.401,
      "spread_vs_prev": -0.03,
      "action": "CUT"
    },
    {
      "expiry": "26MAR2026",
      "dte": 6,
      "total_margin_pct": 33.37,
      "vol_daily": 0.043336,
      "predicted_tomorrow": 31.429,
      "spread_vs_prev": 0.05,
      "action": "CUT"
    },
    {
      "expiry": "26MAR2026",
      "dte": 6,
      "total_margin_pct": 33.32,
      "vol_daily": 0.043267,
      "predicted_tomorrow": 31.382,
      "spread_vs_prev": -0.06,
      "action": "CUT"
    },
    {
      "expiry": "26MAR2026",
      "dte": 6,
      "total_margin_pct": 33.38,
      "vol_daily": 0.043347,
      "predicted_tomorrow": 31.439,
      "spread_vs_prev": -0.3,
      "action": "CUT"
    },
    {
      "expiry": "26MAR2026",
      "dte": 6,
      "total_margin_pct": 33.68,
      "vol_daily": 0.043772,
      "predicted_tomorrow": 31.723,
      "spread_vs_prev": 0.28,
      "action": "CUT"
    },
    {
      "expiry": "26MAR2026",
      "dte": 6,
      "total_margin_pct": 33.4,
      "vol_daily": 0.043382,
      "predicted_tomorrow": 31.458,
      "spread_vs_prev": -0.24,
      "action": "CUT"
    },
    {
      "expiry": "26MAR2026",
      "dte": 6,
      "total_margin_pct": 33.64,
      "vol_daily": 0.043726,
      "predicted_tomorrow": 31.685,
      "spread_vs_prev": 0.02,
      "action": "CUT"
    },
    {
      "expiry": "26MAR2026",
      "dte": 6,
      "total_margin_pct": 33.62,
      "vol_daily": 0.043692,
      "predicted_tomorrow": 31.666,
      "spread_vs_prev": 5.15,
      "action": "CUT"
    },
    {
      "expiry": "27APR2026",
      "dte": 38,
      "total_margin_pct": 28.47,
      "vol_daily": 0.043474,
      "predicted_tomorrow": 27.094,
      "spread_vs_prev": 0.86,
      "action": "CUT"
    },
    {
      "expiry": "27APR2026",
      "dte": 38,
      "total_margin_pct": 27.61,
      "vol_daily": 0.042261,
      "predicted_tomorrow": 26.28,
      "spread_vs_prev": 0.04,
      "action": "CUT"
    },
    {
      "expiry": "27APR2026",
      "dte": 38,
      "total_margin_pct": 27.57,
      "vol_daily": 0.042202,
      "predicted_tomorrow": 26.242,
      "spread_vs_prev": -0.02,
      "action": "CUT"
    },
    {
      "expiry": "27APR2026",
      "dte": 38,
      "total_margin_pct": 27.59,
      "vol_daily": 0.042226,
      "predicted_tomorrow": 26.26,
      "spread_vs_prev": 0.04,
      "action": "CUT"
    },
    {
      "expiry": "27APR2026",
      "dte": 38,
      "total_margin_pct": 27.55,
      "vol_daily": 0.042178,
      "predicted_tomorrow": 26.223,
      "spread_vs_prev": -0.05,
      "action": "CUT"
    },
    {
      "expiry": "27APR2026",
      "dte": 38,
      "total_margin_pct": 27.6,
      "vol_daily": 0.042249,
      "predicted_tomorrow": 26.27,
      "spread_vs_prev": -0.33,
      "action": "CUT"
    },
    {
      "expiry": "27APR2026",
      "dte": 38,
      "total_margin_pct": 27.93,
      "vol_daily": 0.042708,
      "predicted_tomorrow": 26.582,
      "spread_vs_prev": 0.3,
      "action": "CUT"
    },
    {
      "expiry": "27APR2026",
      "dte": 38,
      "total_margin_pct": 27.63,
      "vol_daily": 0.042285,
      "predicted_tomorrow": 26.298,
      "spread_vs_prev": -0.18,
      "action": "CUT"
    },
    {
      "expiry": "27APR2026",
      "dte": 38,
      "total_margin_pct": 27.81,
      "vol_daily": 0.042544,
      "predicted_tomorrow": 26.469,
      "spread_vs_prev": 0.01,
      "action": "CUT"
    },
    {
      "expiry": "27APR2026",
      "dte": 38,
      "total_margin_pct": 27.8,
      "vol_daily": 0.042532,
      "predicted_tomorrow": 26.46,
      "spread_vs_prev": 4.32,
      "action": "CUT"
    },
    {
      "expiry": "26MAY2026",
      "dte": 67,
      "total_margin_pct": 23.48,
      "vol_daily": 0.036318,
      "predicted_tomorrow": 22.365,
      "spread_vs_prev": 0.68,
      "action": "CUT"
    },
    {
      "expiry": "26MAY2026",
      "dte": 67,
      "total_margin_pct": 22.8,
      "vol_daily": 0.035327,
      "predicted_tomorrow": 21.72,
      "spread_vs_prev": 0.03,
      "action": "CUT"
    },
    {
      "expiry": "26MAY2026",
      "dte": 67,
      "total_margin_pct": 22.77,
      "vol_daily": 0.035285,
      "predicted_tomorrow": 21.691,
      "spread_vs_prev": -0.04,
      "action": "CUT"
    },
    {
      "expiry": "26MAY2026",
      "dte": 67,
      "total_margin_pct": 22.81,
      "vol_daily": 0.035341,
      "predicted_tomorrow": 21.729,
      "spread_vs_prev": 0.05,
      "action": "CUT"
    },
    {
      "expiry": "26MAY2026",
      "dte": 67,
      "total_margin_pct": 22.76,
      "vol_daily": 0.03527,
      "predicted_tomorrow": 21.682,
      "spread_vs_prev": -0.03,
      "action": "CUT"
    },
    {
      "expiry": "26MAY2026",
      "dte": 67,
      "total_margin_pct": 22.79,
      "vol_daily": 0.035313,
      "predicted_tomorrow": 21.71,
      "spread_vs_prev": -0.26,
      "action": "CUT"
    },
    {
      "expiry": "26MAY2026",
      "dte": 67,
      "total_margin_pct": 23.05,
      "vol_daily": 0.035693,
      "predicted_tomorrow": 21.957,
      "spread_vs_prev": 0.25,
      "action": "CUT"
    },
    {
      "expiry": "26MAY2026",
      "dte": 67,
      "total_margin_pct": 22.8,
      "vol_daily": 0.035327,
      "predicted_tomorrow": 21.72,
      "spread_vs_prev": -0.13,
      "action": "CUT"
    },
    {
      "expiry": "26MAY2026",
      "dte": 67,
      "total_margin_pct": 22.93,
      "vol_daily": 0.035525,
      "predicted_tomorrow": 21.844,
      "spread_vs_prev": 0.02,
      "action": "CUT"
    },
    {
      "expiry": "26MAY2026",
      "dte": 67,
      "total_margin_pct": 22.91,
      "vol_daily": 0.035496,
      "predicted_tomorrow": 21.825,
      "spread_vs_prev": 0.71,
      "action": "CUT"
    },
    {
      "expiry": "25JUN2026",
      "dte": 97,
      "total_margin_pct": 22.2,
      "vol_daily": 0.034453,
      "predicted_tomorrow": 21.151,
      "spread_vs_prev": 0.67,
      "action": "CUT"
    },
    {
      "expiry": "25JUN2026",
      "dte": 97,
      "total_margin_pct": 21.53,
      "vol_daily": 0.033481,
      "predicted_tomorrow": 20.515,
      "spread_vs_prev": 0.0,
      "action": "CUT"
    },
    {
      "expiry": "25JUN2026",
      "dte": 97,
      "total_margin_pct": 21.53,
      "vol_daily": 0.033481,
      "predicted_tomorrow": 20.515,
      "spread_vs_prev": 0.02,
      "action": "CUT"
    },
    {
      "expiry": "25JUN2026",
      "dte": 97,
      "total_margin_pct": 21.51,
      "vol_daily": 0.033451,
      "predicted_tomorrow": 20.496,
      "spread_vs_prev": -0.1,
      "action": "CUT"
    },
    {
      "expiry": "25JUN2026",
      "dte": 97,
      "total_margin_pct": 21.61,
      "vol_daily": 0.033586,
      "predicted_tomorrow": 20.591,
      "spread_vs_prev": 0.13,
      "action": "CUT"
    },
    {
      "expiry": "25JUN2026",
      "dte": 97,
      "total_margin_pct": 21.48,
      "vol_daily": 0.033407,
      "predicted_tomorrow": 20.468,
      "spread_vs_prev": -0.21,
      "action": "CUT"
    },
    {
      "expiry": "25JUN2026",
      "dte": 97,
      "total_margin_pct": 21.69,
      "vol_daily": 0.033705,
      "predicted_tomorrow": 20.667,
      "spread_vs_prev": -0.04,
      "action": "CUT"
    },
    {
      "expiry": "25JUN2026",
      "dte": 97,
      "total_margin_pct": 21.73,
      "vol_daily": 0.033764,
      "predicted_tomorrow": 20.705,
      "spread_vs_prev": 0.13,
      "action": "CUT"
    },
    {
      "expiry": "25JUN2026",
      "dte": 97,
      "total_margin_pct": 21.6,
      "vol_daily": 0.033571,
      "predicted_tomorrow": 20.581,
      "spread_vs_prev": -0.05,
      "action": "CUT"
    },
    {
      "expiry": "25JUN2026",
      "dte": 97,
      "total_margin_pct": 21.65,
      "vol_daily": 0.033645,
      "predicted_tomorrow": 20.629,
      "spread_vs_prev": -0.98,
      "action": "CUT"
    },
    {
      "expiry": "28JUL2026",
      "dte": 130,
      "total_margin_pct": 22.63,
      "vol_daily": 0.035086,
      "predicted_tomorrow": 21.559,
      "spread_vs_prev": 0.73,
      "action": "CUT"
    },
    {
      "expiry": "28JUL2026",
      "dte": 130,
      "total_margin_pct": 21.9,
      "vol_daily": 0.034015,
      "predicted_tomorrow": 20.866,
      "spread_vs_prev": 0.0,
      "action": "CUT"
    },
    {
      "expiry": "28JUL2026",
      "dte": 130,
      "total_margin_pct": 21.9,
      "vol_daily": 0.034015,
      "predicted_tomorrow": 20.866,
      "spread_vs_prev": 0.0,
      "action": "CUT"
    },
    {
      "expiry": "28JUL2026",
      "dte": 130,
      "total_margin_pct": 21.9,
      "vol_daily": 0.034015,
      "predicted_tomorrow": 20.866,
      "spread_vs_prev": 0.0,
      "action": "CUT"
    },
    {
      "expiry": "28JUL2026",
      "dte": 130,
      "total_margin_pct": 21.9,
      "vol_daily": 0.034015,
      "predicted_tomorrow": 20.866,
      "spread_vs_prev": 0.0,
      "action": "CUT"
    },
    {
      "expiry": "28JUL2026",
      "dte": 130,
      "total_margin_pct": 21.9,
      "vol_daily": 0.034015,
      "predicted_tomorrow": 20.866,
      "spread_vs_prev": 0.0,
      "action": "CUT"
    },
    {
      "expiry": "28JUL2026",
      "dte": 130,
      "total_margin_pct": 21.9,
      "vol_daily": 0.034015,
      "predicted_tomorrow": 20.866,
      "spread_vs_prev": 0.0,
      "action": "CUT"
    },
    {
      "expiry": "28JUL2026",
      "dte": 130,
      "total_margin_pct": 21.9,
      "vol_daily": 0.034015,
      "predicted_tomorrow": 20.866,
      "spread_vs_prev": 0.0,
      "action": "CUT"
    },
    {
      "expiry": "28JUL2026",
      "dte": 130,
      "total_margin_pct": 21.9,
      "vol_daily": 0.034015,
      "predicted_tomorrow": 20.866,
      "spread_vs_prev": -0.08,
      "action": "CUT"
    },
    {
      "expiry": "28JUL2026",
      "dte": 130,
      "total_margin_pct": 21.98,
      "vol_daily": 0.034132,
      "predicted_tomorrow": 20.942,
      "spread_vs_prev": 0.74,
      "action": "CUT"
    },
    {
      "expiry": "26AUG2026",
      "dte": 159,
      "total_margin_pct": 21.24,
      "vol_daily": 0.033045,
      "predicted_tomorrow": 20.24,
      "spread_vs_prev": 0.69,
      "action": "CUT"
    },
    {
      "expiry": "26AUG2026",
      "dte": 159,
      "total_margin_pct": 20.55,
      "vol_daily": 0.032031,
      "predicted_tomorrow": 19.585,
      "spread_vs_prev": 0.0,
      "action": "CUT"
    },
    {
      "expiry": "26AUG2026",
      "dte": 159,
      "total_margin_pct": 20.55,
      "vol_daily": 0.032031,
      "predicted_tomorrow": 19.585,
      "spread_vs_prev": 0.0,
      "action": "CUT"
    },
    {
      "expiry": "26AUG2026",
      "dte": 159,
      "total_margin_pct": 20.55,
      "vol_daily": 0.032031,
      "predicted_tomorrow": 19.585,
      "spread_vs_prev": 0.0,
      "action": "CUT"
    },
    {
      "expiry": "26AUG2026",
      "dte": 159,
      "total_margin_pct": 20.55,
      "vol_daily": 0.032031,
      "predicted_tomorrow": 19.585,
      "spread_vs_prev": 0.0,
      "action": "CUT"
    },
    {
      "expiry": "26AUG2026",
      "dte": 159,
      "total_margin_pct": 20.55,
      "vol_daily": 0.032031,
      "predicted_tomorrow": 19.585,
      "spread_vs_prev": 0.0,
      "action": "CUT"
    },
    {
      "expiry": "26AUG2026",
      "dte": 159,
      "total_margin_pct": 20.55,
      "vol_daily": 0.032031,
      "predicted_tomorrow": 19.585,
      "spread_vs_prev": -0.83,
      "action": "CUT"
    },
    {
      "expiry": "26AUG2026",
      "dte": 159,
      "total_margin_pct": 21.38,
      "vol_daily": 0.033257,
      "predicted_tomorrow": 20.373,
      "spread_vs_prev": 0.0,
      "action": "CUT"
    },
    {
      "expiry": "26AUG2026",
      "dte": 159,
      "total_margin_pct": 21.38,
      "vol_daily": 0.033257,
      "predicted_tomorrow": 20.373,
      "spread_vs_prev": 0.0,
      "action": "CUT"
    },
    {
      "expiry": "26AUG2026",
      "dte": 159,
      "total_margin_pct": 21.38,
      "vol_daily": 0.033257,
      "predicted_tomorrow": 20.373,
      "spread_vs_prev": 0.0,
      "action": "CUT"
    }
  ]
}